Metadata-Version: 2.1
Name: Gbemisola_Math_General
Version: 1.2
Summary: Gbemisola Math General find the squar root, squar, area of triangle, recteangle and sqaur and generate a random number from any number range 
Author: ALADETOYINBO GBEMISOLA IBIERE
Author-email: megbopegbemisola96@gmail.com
License-File: license.txt
